uw_bridge/VERSION
uw_bridge/__init__.py
uw_bridge/custom_fields.py
uw_bridge/dao.py
uw_bridge/models.py
uw_bridge/test.py
uw_bridge/user_roles.py
uw_bridge/users.py
uw_bridge/util.py
uw_bridge/resources/bridge/file/api/admin/users.POST
uw_bridge/resources/bridge/file/api/admin/users/195.DELETE
uw_bridge/resources/bridge/file/api/admin/users/195.DELETE.http-headers
uw_bridge/resources/bridge/file/api/admin/users/uid%3Ajaverage%40uw%2Eedu.DELETE
uw_bridge/resources/bridge/file/api/admin/users/uid%3Ajaverage%40uw%2Eedu.DELETE.http-headers
uw_bridge/resources/bridge/file/api/admin/users/17637/roles/batch.PUT
uw_bridge/resources/bridge/file/api/admin/users/uid%3Abill%40uw%2Eedu/roles/batch.PUT
uw_bridge/resources/bridge/file/api/author/custom_fields
uw_bridge/resources/bridge/file/api/author/roles
uw_bridge/resources/bridge/file/api/author/users_after_xxx_includes%5B%5D_
uw_bridge/resources/bridge/file/api/author/users_after_xxx_includes%5B%5D_custom_fields
uw_bridge/resources/bridge/file/api/author/users_includes%5B%5D__limit_1000
uw_bridge/resources/bridge/file/api/author/users_includes%5B%5D__role_author_limit_1000
uw_bridge/resources/bridge/file/api/author/users_includes%5B%5D_custom_fields_limit_1000
uw_bridge/resources/bridge/file/api/author/users/17637.PATCH
uw_bridge/resources/bridge/file/api/author/users/17637_includes%5B%5D_custom_fields.PATCH
uw_bridge/resources/bridge/file/api/author/users/17637_includes%5B%5D_custom_fields_includes%5B%5D_course_summary_includes%5B%5D_manager
uw_bridge/resources/bridge/file/api/author/users/17637_includes%5B%5D_custom_fields_includes%5B%5D_course_summary_includes%5B%5D_manager_with_deleted_true
uw_bridge/resources/bridge/file/api/author/users/uid%3Abill%40uw%2Eedu.PATCH
uw_bridge/resources/bridge/file/api/author/users/uid%3Abill%40uw%2Eedu_includes%5B%5D_custom_fields_includes%5B%5D_course_summary_includes%5B%5D_manager
uw_bridge/resources/bridge/file/api/author/users/uid%3Ajaverage%40uw%2Eedu_includes%5B%5D_custom_fields
uw_restclients_bridge-1.6.5.dist-info/licenses/LICENSE
uw_restclients_bridge-1.6.5.dist-info/METADATA
uw_restclients_bridge-1.6.5.dist-info/WHEEL
uw_restclients_bridge-1.6.5.dist-info/top_level.txt
uw_restclients_bridge-1.6.5.dist-info/RECORD
